exceeddata/sdk/__init__.py
exceeddata/sdk/blf.py
exceeddata/sdk/converter.py
exceeddata/sdk/vdata.py
exceeddata_sdk_vdata-2.10.5.dist-info/LICENSE
exceeddata_sdk_vdata-2.10.5.dist-info/METADATA
exceeddata_sdk_vdata-2.10.5.dist-info/WHEEL
exceeddata_sdk_vdata-2.10.5.dist-info/top_level.txt
exceeddata_sdk_vdata-2.10.5.dist-info/RECORD
