Metadata-Version: 2.1
Name: exceeddata-sdk-vdata
Version: 2.10.5
Summary: ExceedData vData SDK for Python
Home-page: http://www.smartsct.com
Author: Nick Xie
Author-email: nickxie@smartsct.com
License: MIT
Platform: UNKNOWN
Classifier: Development Status :: 4 - Beta
Classifier: Intended Audience :: Developers
Classifier: License :: OSI Approved :: MIT License
Classifier: Programming Language :: Python :: 3
Classifier: Topic :: Software Development :: Libraries :: Python Modules
Requires-Dist: python-snappy
Requires-Dist: zstd
